q_searcher/__init__.py
q_searcher/const.py
q_searcher/init.py
q_searcher/search.py
q_searcher-0.0.3.dist-info/LICENSE
q_searcher-0.0.3.dist-info/WHEEL
q_searcher-0.0.3.dist-info/METADATA
q_searcher-0.0.3.dist-info/RECORD
