Metadata-Version: 2.1
Name: q-searcher
Version: 0.0.3
Summary: 
Author: UioSun
Author-email: uiosun@outlook.com
Requires-Python: >=3.10,<4.0
Classifier: License :: OSI Approved :: MIT License
Classifier: Operating System :: OS Independent
Classifier: Programming Language :: Python :: 3
Classifier: Programming Language :: Python :: 3.10
Project-URL: Homepage, https://github.com/freedom-island/q_searcher
Project-URL: Issues, https://github.com/freedom-island/q_searcher/issues
Project-URL: Website, https://www.uiosun.com/libs/q_searcher
